{
  "updated_at": "2026-06-04 02:42:11",
  "candidates": [
    {
      "party": "더불어민주당",
      "name": "정원오",
      "votes": 1467234,
      "rate": 53.73
    },
    {
      "party": "국민의힘",
      "name": "오세훈",
      "votes": 1189834,
      "rate": 43.57
    },
    {
      "party": "개혁신당",
      "name": "김정철",
      "votes": 21875,
      "rate": 0.8
    },
    {
      "party": "여성의당",
      "name": "유지혜",
      "votes": 22365,
      "rate": 0.81
    },
    {
      "party": "정의당",
      "name": "권영국",
      "votes": 29247,
      "rate": 1.07
    }
  ]
}