{
  "updated_at": "2026-06-04 02:10:17",
  "candidates": [
    {
      "party": "더불어민주당",
      "name": "정원오",
      "votes": 1339265,
      "rate": 55.0
    },
    {
      "party": "국민의힘",
      "name": "오세훈",
      "votes": 1030583,
      "rate": 42.32
    },
    {
      "party": "개혁신당",
      "name": "김정철",
      "votes": 19339,
      "rate": 0.79
    },
    {
      "party": "여성의당",
      "name": "유지혜",
      "votes": 19412,
      "rate": 0.79
    },
    {
      "party": "정의당",
      "name": "권영국",
      "votes": 26176,
      "rate": 1.07
    }
  ]
}